mcp_aim_crawler/mcp_aim_crawler/__init__.py
mcp_aim_crawler/mcp_aim_crawler/crawler.py
mcp_aim_crawler/mcp_aim_crawler/logger.py
mcp_aim_crawler/mcp_aim_crawler/mcp_server.py
mcp_aim_crawler/tests/__init__.py
mcp_aim_crawler/tests/test_crawler.py
mcp_aim_crawler-0.1.0.dist-info/METADATA
mcp_aim_crawler-0.1.0.dist-info/WHEEL
mcp_aim_crawler-0.1.0.dist-info/RECORD
