Metadata-Version: 2.4
Name: mcp_aim_crawler
Version: 0.1.0
Summary: Web crawler for datatist.com
Project-URL: Repository, https://github.com/zhaoxin34/mcp_aim_crawler
Project-URL: Issues, https://github.com/zhaoxin34/mcp_aim_crawler/issues
Author-email: zhaoxin <zhaoxin3456@gmail.com>
License-Expression: MIT
Keywords: datatist,mcp,web crawler
Classifier: Development Status :: 3 - Alpha
Classifier: Intended Audience :: Developers
Classifier: License :: OSI Approved :: MIT License
Classifier: Programming Language :: Python :: 3
Classifier: Programming Language :: Python :: 3.12
Classifier: Topic :: Internet :: WWW/HTTP :: Dynamic Content
Classifier: Topic :: Software Development :: Libraries :: Python Modules
Requires-Python: >=3.12.9
Requires-Dist: beautifulsoup4>=4.12.0
Requires-Dist: mcp[cli]>=1.4.1
Requires-Dist: playwright>=1.42.0
Requires-Dist: python-dotenv>=1.0.0
Requires-Dist: requests>=2.31.0
Provides-Extra: dev
Requires-Dist: black>=24.2.0; extra == 'dev'
Requires-Dist: isort>=5.13.0; extra == 'dev'
Requires-Dist: pytest-cov>=4.1.0; extra == 'dev'
Requires-Dist: pytest>=8.0.0; extra == 'dev'
